{
  "project_info": {
    "project_number": "147544006563",
    "project_id": "project-money-buddy",
    "storage_bucket": "project-money-buddy.appspot.com"
  },
  "client": [
    {
      "client_info": {
        "mobilesdk_app_id": "1:147544006563:android:4e1c3e53a82c74e96c4416",
        "android_client_info": {
          "package_name": "com.example.money_buddy_mobile"
        }
      },
      "oauth_client": [
        {
          "client_id": "147544006563-k06qfojggto8ubn6kvsjhjtkpcdck768.apps.googleusercontent.com",
          "client_type": 3
        }
      ],
      "api_key": [
        {
          "current_key": "AIzaSyBjatEwFj7erxel7j_ZPFY3t1d5n0GMkZs"
        }
      ],
      "services": {
        "appinvite_service": {
          "other_platform_oauth_client": [
            {
              "client_id": "147544006563-k06qfojggto8ubn6kvsjhjtkpcdck768.apps.googleusercontent.com",
              "client_type": 3
            },
            {
              "client_id": "147544006563-tlo0ab52e50tnsf3svor32p6mt0sm6e9.apps.googleusercontent.com",
              "client_type": 2,
              "ios_info": {
                "bundle_id": "com.example.moneyBuddyMobile"
              }
            }
          ]
        }
      }
    }
  ],
  "configuration_version": "1"
}